hyperscript_dump.py
hyperscript_dump-1.0.4.dist-info/licenses/LICENSE
hyperscript_dump-1.0.4.dist-info/METADATA
hyperscript_dump-1.0.4.dist-info/WHEEL
hyperscript_dump-1.0.4.dist-info/top_level.txt
hyperscript_dump-1.0.4.dist-info/RECORD
