Metadata-Version: 2.4
Name: hyperscript-dump
Version: 1.0.4
Summary: Convert Python data structures into Hyperscript-compatible code blocks.
Author-email: Lucas Lorenz <LukeLorenzBA@gmail.com>
License: MIT
Project-URL: Homepage, https://github.com/LucLor06/hyperscript-dump
Project-URL: Repository, https://github.com/LucLor06/hyperscript-dump
Project-URL: Changelog, https://github.com/LucLor06/hyperscript-dump/blob/main/CHANGELOG.md
Keywords: hyperscript,python
Classifier: Development Status :: 3 - Alpha
Classifier: Intended Audience :: Developers
Classifier: License :: OSI Approved :: MIT License
Classifier: Programming Language :: Python :: 3
Classifier: Programming Language :: Python :: 3.7
Classifier: Programming Language :: Python :: 3.8
Classifier: Programming Language :: Python :: 3.9
Classifier: Programming Language :: Python :: 3.10
Classifier: Programming Language :: Python :: 3.11
Classifier: Programming Language :: Python :: 3.12
Classifier: Topic :: Software Development :: Libraries
Classifier: Topic :: Utilities
Requires-Python: >=3.7
License-File: LICENSE
Dynamic: license-file
